sqlite_utils_sqlite_regex/__init__.py
sqlite_utils_sqlite_regex/version.py
sqlite_utils_sqlite_regex-0.2.3.dist-info/METADATA
sqlite_utils_sqlite_regex-0.2.3.dist-info/WHEEL
sqlite_utils_sqlite_regex-0.2.3.dist-info/entry_points.txt
sqlite_utils_sqlite_regex-0.2.3.dist-info/top_level.txt
sqlite_utils_sqlite_regex-0.2.3.dist-info/RECORD
